pygpeg/__init__.py
pygpeg/exceptions.py
pygpeg/helpers.py
pygpeg/mixins.py
pygpeg/parser.py
pygpeg/symbols.py
pygpeg-0.1.0.dist-info/METADATA
pygpeg-0.1.0.dist-info/WHEEL
pygpeg-0.1.0.dist-info/RECORD
